LICENSE
README.md
setup.py
SecProj.egg-info/PKG-INFO
SecProj.egg-info/SOURCES.txt
SecProj.egg-info/dependency_links.txt
SecProj.egg-info/requires.txt
SecProj.egg-info/top_level.txt
secproj/__init__.py
secproj/core.py