Metadata-Version: 2.1
Name: SecProj
Version: 1.0.1
Summary: Simple tools to help you secure your projects in a more simple manner, allowing for simple and secure development.
Home-page: https://github.com/basegodfelix/secproj
Author: Felix Hernandez
License: MIT
Platform: UNKNOWN
License-File: LICENSE
